setup.py
pycmdliner/__init__.py
pycmdliner/pycmdliner.py
pycmdliner.egg-info/PKG-INFO
pycmdliner.egg-info/SOURCES.txt
pycmdliner.egg-info/dependency_links.txt
pycmdliner.egg-info/top_level.txt
tests/baseNoParameter.py