Metadata-Version: 1.0
Name: pycmdliner
Version: 0.1.0
Summary: A scaffolding module for command line applications: It manages input commands and parameters invoking provided business logic.
Home-page: https://github.com/fpacifici/pyCmdLiner
Author: Filippo Pacifici
Author-email: filippo.pacifici@gmail.com
License: Apache
Keywords: commandline tools scaffolding
Platform: UNKNOWN
Classifier: Development Status :: 3 - Alpha
Classifier: Topic :: Software Development :: Libraries
Classifier: License :: OSI Approved :: Apache Software License
